<annotation>
	<folder>Train</folder>
	<filename>A-3.jpg</filename>
	<path>H:\resizeimage\Train\A-3.jpg</path>
	<source>
		<database>Unknown</database>
	</source>
	<size>
		<width>449</width>
		<height>600</height>
		<depth>3</depth>
	</size>
	<segmented>0</segmented>
	<object>
		<name>Akshaya</name>
		<pose>Unspecified</pose>
		<truncated>0</truncated>
		<difficult>0</difficult>
		<bndbox>
			<xmin>140</xmin>
			<ymin>72</ymin>
			<xmax>381</xmax>
			<ymax>389</ymax>
		</bndbox>
	</object>
</annotation>
