<annotation>
	<folder>Train</folder>
	<filename>V-3.jpg.jpg</filename>
	<path>H:\resizeimage\Train\V-3.jpg.jpg</path>
	<source>
		<database>Unknown</database>
	</source>
	<size>
		<width>187</width>
		<height>270</height>
		<depth>3</depth>
	</size>
	<segmented>0</segmented>
	<object>
		<name>Vijay</name>
		<pose>Unspecified</pose>
		<truncated>0</truncated>
		<difficult>0</difficult>
		<bndbox>
			<xmin>31</xmin>
			<ymin>63</ymin>
			<xmax>85</xmax>
			<ymax>145</ymax>
		</bndbox>
	</object>
</annotation>
